{
  "b": 209,
  "disableInputWhenNotFocused": true,
  "mangledName": "Title",
  "name": "Title",
  "r": 209,
  "standardSortMethod": true,
  "stopSoundsOnStartup": true,
  "title": "",
  "v": 209,
  "uiSettings": {
    "grid": false,
    "gridType": "rectangular",
    "gridWidth": 32,
    "gridHeight": 32,
    "gridOffsetX": 0,
    "gridOffsetY": 0,
    "gridColor": 10401023,
    "gridAlpha": 0.8,
    "snap": false,
    "zoomFactor": 0.5653158055126307,
    "windowMask": false
  },
  "objectsGroups": [],
  "variables": [],
  "instances": [
    {
      "angle": 0,
      "customSize": false,
      "height": 0,
      "keepRatio": true,
      "layer": "",
      "name": "YellowButton",
      "persistentUuid": "e26205e5-843e-4359-8ce6-5c8bea6bce12",
      "width": 0,
      "x": 482,
      "y": 287,
      "zOrder": 1,
      "numberProperties": [],
      "stringProperties": [],
      "initialVariables": []
    },
    {
      "angle": 0,
      "customSize": false,
      "height": 0,
      "keepRatio": true,
      "layer": "",
      "name": "titleText",
      "persistentUuid": "c6a64b1f-04ef-487a-bfc6-8868cfae1036",
      "width": 0,
      "x": 455,
      "y": 187,
      "zOrder": 2,
      "numberProperties": [],
      "stringProperties": [],
      "initialVariables": []
    }
  ],
  "objects": [
    {
      "assetStoreId": "615de0316452630b9f4f6a39decc82e2449b82c1afd1ff24d6470dad2922177b",
      "name": "YellowButton",
      "type": "PanelSpriteButton::PanelSpriteButton",
      "variables": [],
      "effects": [],
      "behaviors": [],
      "content": {
        "LeftPadding": 16,
        "RightPadding": 16,
        "PressedLabelOffsetY": 10,
        "BottomPadding": 32,
        "TopPadding": 16,
        "HoveredFadeOutDuration": 0.25
      },
      "childrenContent": {
        "Hovered": {
          "bottomMargin": 32,
          "height": 106,
          "leftMargin": 16,
          "rightMargin": 16,
          "texture": "Yellow Button_Hovered.png",
          "tiled": true,
          "topMargin": 16,
          "width": 256
        },
        "Idle": {
          "bottomMargin": 32,
          "height": 106,
          "leftMargin": 16,
          "rightMargin": 16,
          "texture": "Yellow Button_Idle.png",
          "tiled": true,
          "topMargin": 16,
          "width": 256
        },
        "Label": {
          "bold": false,
          "italic": false,
          "smoothed": true,
          "underlined": false,
          "string": "Start",
          "font": "",
          "textAlignment": "center",
          "characterSize": 60,
          "color": {
            "b": 42,
            "g": 87,
            "r": 139
          },
          "content": {
            "bold": false,
            "isOutlineEnabled": false,
            "isShadowEnabled": false,
            "italic": false,
            "outlineColor": "255;255;255",
            "outlineThickness": 2,
            "shadowAngle": 90,
            "shadowBlurRadius": 2,
            "shadowColor": "0;0;0",
            "shadowDistance": 4,
            "shadowOpacity": 127,
            "smoothed": true,
            "underlined": false,
            "text": "Start",
            "font": "",
            "textAlignment": "center",
            "verticalTextAlignment": "top",
            "characterSize": 60,
            "color": "139;87;42"
          }
        },
        "Pressed": {
          "bottomMargin": 16,
          "height": 106,
          "leftMargin": 16,
          "rightMargin": 16,
          "texture": "Yellow Button_Pressed.png",
          "tiled": true,
          "topMargin": 32,
          "width": 256
        }
      }
    },
    {
      "assetStoreId": "",
      "bold": false,
      "italic": false,
      "name": "titleText",
      "smoothed": true,
      "type": "TextObject::Text",
      "underlined": false,
      "variables": [],
      "effects": [],
      "behaviors": [],
      "string": "Nozama Driver",
      "font": "",
      "textAlignment": "left",
      "characterSize": 50,
      "color": {
        "b": 0,
        "g": 0,
        "r": 0
      },
      "content": {
        "bold": false,
        "isOutlineEnabled": false,
        "isShadowEnabled": false,
        "italic": false,
        "outlineColor": "255;255;255",
        "outlineThickness": 2,
        "shadowAngle": 90,
        "shadowBlurRadius": 2,
        "shadowColor": "0;0;0",
        "shadowDistance": 4,
        "shadowOpacity": 127,
        "smoothed": true,
        "underlined": false,
        "text": "Nozama Driver",
        "font": "",
        "textAlignment": "left",
        "verticalTextAlignment": "top",
        "characterSize": 50,
        "color": "0;0;0"
      }
    }
  ],
  "objectsFolderStructure": {
    "folderName": "__ROOT",
    "children": [
      {
        "objectName": "YellowButton"
      },
      {
        "objectName": "titleText"
      }
    ]
  },
  "events": [
    {
      "type": "BuiltinCommonInstructions::Standard",
      "conditions": [
        {
          "type": {
            "value": "SourisSurObjet"
          },
          "parameters": [
            "YellowButton",
            "",
            "",
            ""
          ]
        },
        {
          "type": {
            "value": "BuiltinCommonInstructions::Once"
          },
          "parameters": []
        }
      ],
      "actions": [
        {
          "type": {
            "value": "PlaySound"
          },
          "parameters": [
            "",
            "Sounds\\Button Touch.mp3",
            "",
            "40",
            "1.4"
          ]
        }
      ]
    },
    {
      "type": "BuiltinCommonInstructions::Standard",
      "conditions": [
        {
          "type": {
            "value": "PanelSpriteButton::PanelSpriteButton::IsClicked"
          },
          "parameters": [
            "YellowButton",
            ""
          ]
        }
      ],
      "actions": [
        {
          "type": {
            "value": "Scene"
          },
          "parameters": [
            "",
            "\"Level 1\"",
            ""
          ]
        },
        {
          "type": {
            "value": "PlaySound"
          },
          "parameters": [
            "",
            "Sounds\\Start Game.wav",
            "",
            "40",
            ""
          ]
        }
      ]
    }
  ],
  "layers": [
    {
      "ambientLightColorB": 200,
      "ambientLightColorG": 200,
      "ambientLightColorR": 200,
      "camera3DFarPlaneDistance": 10000,
      "camera3DFieldOfView": 45,
      "camera3DNearPlaneDistance": 3,
      "cameraType": "",
      "followBaseLayerCamera": false,
      "isLightingLayer": false,
      "isLocked": false,
      "name": "",
      "renderingType": "",
      "visibility": true,
      "cameras": [
        {
          "defaultSize": true,
          "defaultViewport": true,
          "height": 0,
          "viewportBottom": 1,
          "viewportLeft": 0,
          "viewportRight": 1,
          "viewportTop": 0,
          "width": 0
        }
      ],
      "effects": [
        {
          "effectType": "Scene3D::HemisphereLight",
          "name": "3D Light",
          "doubleParameters": {
            "elevation": 45,
            "intensity": 1,
            "rotation": 0
          },
          "stringParameters": {
            "groundColor": "64;64;64",
            "skyColor": "255;255;255",
            "top": "Y-"
          },
          "booleanParameters": {}
        }
      ]
    }
  ],
  "behaviorsSharedData": [
    {
      "name": "Animation",
      "type": "AnimatableCapability::AnimatableBehavior"
    },
    {
      "name": "Effect",
      "type": "EffectCapability::EffectBehavior"
    },
    {
      "name": "FireBullet",
      "type": "FireBullet::FireBullet"
    },
    {
      "name": "Flash",
      "type": "Flash::Flash"
    },
    {
      "name": "Flippable",
      "type": "FlippableCapability::FlippableBehavior"
    },
    {
      "name": "Health",
      "type": "Health::Health"
    },
    {
      "name": "InOnScreen",
      "type": "IsOnScreen::InOnScreen"
    },
    {
      "name": "Opacity",
      "type": "OpacityCapability::OpacityBehavior"
    },
    {
      "name": "PixelPerfectTopDownMovement",
      "type": "PixelPerfectMovement::PixelPerfectTopDownMovement"
    },
    {
      "name": "Resizable",
      "type": "ResizableCapability::ResizableBehavior"
    },
    {
      "name": "Scale",
      "type": "ScalableCapability::ScalableBehavior"
    },
    {
      "name": "SmoothCamera",
      "type": "SmoothCamera::SmoothCamera"
    },
    {
      "name": "Text",
      "type": "TextContainerCapability::TextContainerBehavior"
    },
    {
      "name": "TopDownMovement",
      "type": "TopDownMovementBehavior::TopDownMovementBehavior"
    }
  ]
}